{"eeebe75c09f018648eca21bf7781130d:d41d8cd98f00b204e9800998ecf8427e":{"statistic":{"failed":0,"broken":0,"skipped":0,"passed":1,"unknown":0,"total":1},"items":[{"uid":"8ded3c96a7f64f5b","reportUrl":"https://bredah.github.io/api-rest/8//#testresult/8ded3c96a7f64f5b","status":"passed","time":{"start":1724700877789,"stop":1724700877790,"duration":1}}]},"82c1c96f9d889ebc54d1f7860e9d24ef:d41d8cd98f00b204e9800998ecf8427e":{"statistic":{"failed":0,"broken":0,"skipped":0,"passed":1,"unknown":0,"total":1},"items":[{"uid":"3976df9eae82e693","reportUrl":"https://bredah.github.io/api-rest/8//#testresult/3976df9eae82e693","status":"passed","time":{"start":1724700877934,"stop":1724700877935,"duration":1}}]},"2fe94bbd6e1d0d530af223501543f263:d41d8cd98f00b204e9800998ecf8427e":{"statistic":{"failed":0,"broken":0,"skipped":0,"passed":1,"unknown":0,"total":1},"items":[{"uid":"919b8bf80db06c77","reportUrl":"https://bredah.github.io/api-rest/8//#testresult/919b8bf80db06c77","status":"passed","time":{"start":1724700881687,"stop":1724700881725,"duration":38}}]},"b4e124c9510a0a3b7a46d708e69f6678:d41d8cd98f00b204e9800998ecf8427e":{"statistic":{"failed":0,"broken":0,"skipped":0,"passed":1,"unknown":0,"total":1},"items":[{"uid":"c29b215427745ef7","reportUrl":"https://bredah.github.io/api-rest/8//#testresult/c29b215427745ef7","status":"passed","time":{"start":1724700877952,"stop":1724700877955,"duration":3}}]},"a84c5c489b3568932b5495f3c8f73c75:d41d8cd98f00b204e9800998ecf8427e":{"statistic":{"failed":0,"broken":0,"skipped":0,"passed":1,"unknown":0,"total":1},"items":[{"uid":"fa2bf1a995555396","reportUrl":"https://bredah.github.io/api-rest/8//#testresult/fa2bf1a995555396","status":"passed","time":{"start":1724700880012,"stop":1724700880056,"duration":44}}]},"18c32ebc21e7e49d1eddf0179b254181:d41d8cd98f00b204e9800998ecf8427e":{"statistic":{"failed":0,"broken":0,"skipped":0,"passed":1,"unknown":0,"total":1},"items":[{"uid":"a1f8b2fe556ac69b","reportUrl":"https://bredah.github.io/api-rest/8//#testresult/a1f8b2fe556ac69b","status":"passed","time":{"start":1724700877911,"stop":1724700877922,"duration":11}}]},"903565bb4a4882b3b9a6863ebd4b6c49:d41d8cd98f00b204e9800998ecf8427e":{"statistic":{"failed":0,"broken":0,"skipped":0,"passed":1,"unknown":0,"total":1},"items":[{"uid":"9b03cb66caeff27","reportUrl":"https://bredah.github.io/api-rest/8//#testresult/9b03cb66caeff27","status":"passed","time":{"start":1724700877930,"stop":1724700877931,"duration":1}}]},"d835dd7f4e3011017b6d0178b230e8c2:d41d8cd98f00b204e9800998ecf8427e":{"statistic":{"failed":0,"broken":0,"skipped":0,"passed":1,"unknown":0,"total":1},"items":[{"uid":"65c010b2e7fd9d4d","reportUrl":"https://bredah.github.io/api-rest/8//#testresult/65c010b2e7fd9d4d","status":"passed","time":{"start":1724700877787,"stop":1724700877788,"duration":1}}]},"1a2dc4fb26d2634e11cb3d72b594d204:d41d8cd98f00b204e9800998ecf8427e":{"statistic":{"failed":0,"broken":0,"skipped":0,"passed":1,"unknown":0,"total":1},"items":[{"uid":"81cf39b72e98cc7d","reportUrl":"https://bredah.github.io/api-rest/8//#testresult/81cf39b72e98cc7d","status":"passed","time":{"start":1724700877924,"stop":1724700877927,"duration":3}}]},"11405a0bfe40866491540a9c0b1fa1ea:d41d8cd98f00b204e9800998ecf8427e":{"statistic":{"failed":0,"broken":0,"skipped":0,"passed":1,"unknown":0,"total":1},"items":[{"uid":"142ebaab8564ed01","reportUrl":"https://bredah.github.io/api-rest/8//#testresult/142ebaab8564ed01","status":"passed","time":{"start":1724700880059,"stop":1724700880067,"duration":8}}]},"532a4a61df7c9c4185111ec6508a81fc:d41d8cd98f00b204e9800998ecf8427e":{"statistic":{"failed":0,"broken":0,"skipped":0,"passed":1,"unknown":0,"total":1},"items":[{"uid":"2ac122adb4e315d4","reportUrl":"https://bredah.github.io/api-rest/8//#testresult/2ac122adb4e315d4","status":"passed","time":{"start":1724700877928,"stop":1724700877929,"duration":1}}]},"1e7c31d57b740f3a5a8cf0e57f7aea3a:d41d8cd98f00b204e9800998ecf8427e":{"statistic":{"failed":0,"broken":0,"skipped":0,"passed":1,"unknown":0,"total":1},"items":[{"uid":"3690d6063c6d4dbd","reportUrl":"https://bredah.github.io/api-rest/8//#testresult/3690d6063c6d4dbd","status":"passed","time":{"start":1724700877774,"stop":1724700877785,"duration":11}}]},"3323f80a050aca7fcee506bb2cc34cc3:d41d8cd98f00b204e9800998ecf8427e":{"statistic":{"failed":0,"broken":0,"skipped":0,"passed":1,"unknown":0,"total":1},"items":[{"uid":"e85541ee7ddd0447","reportUrl":"https://bredah.github.io/api-rest/8//#testresult/e85541ee7ddd0447","status":"passed","time":{"start":1724700877933,"stop":1724700877934,"duration":1}}]},"d445699ecb26845798c5d5ae4920a554:d41d8cd98f00b204e9800998ecf8427e":{"statistic":{"failed":0,"broken":0,"skipped":0,"passed":1,"unknown":0,"total":1},"items":[{"uid":"74e6ea451ef9c34b","reportUrl":"https://bredah.github.io/api-rest/8//#testresult/74e6ea451ef9c34b","status":"passed","time":{"start":1724700877931,"stop":1724700877932,"duration":1}}]},"4ae331cfe512034daebe8d0a69de491d:d41d8cd98f00b204e9800998ecf8427e":{"statistic":{"failed":0,"broken":0,"skipped":0,"passed":1,"unknown":0,"total":1},"items":[{"uid":"802f238cacc19b38","reportUrl":"https://bredah.github.io/api-rest/8//#testresult/802f238cacc19b38","status":"passed","time":{"start":1724700877748,"stop":1724700877759,"duration":11}}]},"27ebbfef89615dd18cf16b65e9d6e897:d41d8cd98f00b204e9800998ecf8427e":{"statistic":{"failed":0,"broken":0,"skipped":0,"passed":1,"unknown":0,"total":1},"items":[{"uid":"718b941921b4e88f","reportUrl":"https://bredah.github.io/api-rest/8//#testresult/718b941921b4e88f","status":"passed","time":{"start":1724700877786,"stop":1724700877787,"duration":1}}]},"0d3ada05ec7474662c06d6a31a2d355a:d41d8cd98f00b204e9800998ecf8427e":{"statistic":{"failed":0,"broken":0,"skipped":0,"passed":1,"unknown":0,"total":1},"items":[{"uid":"b4c9f897a8730c14","reportUrl":"https://bredah.github.io/api-rest/8//#testresult/b4c9f897a8730c14","status":"passed","time":{"start":1724700879821,"stop":1724700879837,"duration":16}}]},"1c1d2be4aa4fa56d2a620e3f4a2042c3:d41d8cd98f00b204e9800998ecf8427e":{"statistic":{"failed":0,"broken":0,"skipped":0,"passed":1,"unknown":0,"total":1},"items":[{"uid":"da5bf5195061db98","reportUrl":"https://bredah.github.io/api-rest/8//#testresult/da5bf5195061db98","status":"passed","time":{"start":1724700877943,"stop":1724700877945,"duration":2}}]},"e9fe4616e6a293491bbbba42a2aeb395:d41d8cd98f00b204e9800998ecf8427e":{"statistic":{"failed":0,"broken":0,"skipped":0,"passed":1,"unknown":0,"total":1},"items":[{"uid":"bf8ce4b460e2017b","reportUrl":"https://bredah.github.io/api-rest/8//#testresult/bf8ce4b460e2017b","status":"passed","time":{"start":1724700877946,"stop":1724700877950,"duration":4}}]},"760282bce5eb9c325db0b63e64f0caaa:d41d8cd98f00b204e9800998ecf8427e":{"statistic":{"failed":0,"broken":0,"skipped":0,"passed":1,"unknown":0,"total":1},"items":[{"uid":"115a338f4ae0b02a","reportUrl":"https://bredah.github.io/api-rest/8//#testresult/115a338f4ae0b02a","status":"passed","time":{"start":1724700879852,"stop":1724700879856,"duration":4}}]},"e4b7812bf50840eb552a6c6bf7e653dc:d41d8cd98f00b204e9800998ecf8427e":{"statistic":{"failed":0,"broken":0,"skipped":0,"passed":1,"unknown":0,"total":1},"items":[{"uid":"3048ff66e93c08cc","reportUrl":"https://bredah.github.io/api-rest/8//#testresult/3048ff66e93c08cc","status":"passed","time":{"start":1724700877775,"stop":1724700877802,"duration":27}}]},"8b8402f9b03bdf49bc0e38b9e9430e37:d41d8cd98f00b204e9800998ecf8427e":{"statistic":{"failed":0,"broken":0,"skipped":0,"passed":1,"unknown":0,"total":1},"items":[{"uid":"4978a91053e0dede","reportUrl":"https://bredah.github.io/api-rest/8//#testresult/4978a91053e0dede","status":"passed","time":{"start":1724700881737,"stop":1724700881742,"duration":5}}]},"01cec109c4af8c38341ae6a2216fbdac:d41d8cd98f00b204e9800998ecf8427e":{"statistic":{"failed":0,"broken":0,"skipped":0,"passed":1,"unknown":0,"total":1},"items":[{"uid":"5c2315cbafec32bd","reportUrl":"https://bredah.github.io/api-rest/8//#testresult/5c2315cbafec32bd","status":"passed","time":{"start":1724700877950,"stop":1724700877951,"duration":1}}]},"f52eb42c18d6aa1c488fe5cfd2e3340b:d41d8cd98f00b204e9800998ecf8427e":{"statistic":{"failed":0,"broken":0,"skipped":0,"passed":1,"unknown":0,"total":1},"items":[{"uid":"4913534d9b0ee397","reportUrl":"https://bredah.github.io/api-rest/8//#testresult/4913534d9b0ee397","status":"passed","time":{"start":1724700877936,"stop":1724700877943,"duration":7}}]},"adcfc58ca5734f59a415fa0fdea1dc38:d41d8cd98f00b204e9800998ecf8427e":{"statistic":{"failed":0,"broken":0,"skipped":0,"passed":1,"unknown":0,"total":1},"items":[{"uid":"9de98778e112fc4e","reportUrl":"https://bredah.github.io/api-rest/8//#testresult/9de98778e112fc4e","status":"passed","time":{"start":1724700879839,"stop":1724700879844,"duration":5}}]},"763c1fcc4dadf83903bb18c3de50a400:d41d8cd98f00b204e9800998ecf8427e":{"statistic":{"failed":0,"broken":0,"skipped":0,"passed":1,"unknown":0,"total":1},"items":[{"uid":"823644566fff67d3","reportUrl":"https://bredah.github.io/api-rest/8//#testresult/823644566fff67d3","status":"passed","time":{"start":1724700877805,"stop":1724700877807,"duration":2}}]},"53ac4b8eb7235e0cec60f3ab4080898b:d41d8cd98f00b204e9800998ecf8427e":{"statistic":{"failed":0,"broken":0,"skipped":0,"passed":1,"unknown":0,"total":1},"items":[{"uid":"dafd22db834f9c6e","reportUrl":"https://bredah.github.io/api-rest/8//#testresult/dafd22db834f9c6e","status":"passed","time":{"start":1724700879845,"stop":1724700879851,"duration":6}}]}}